etra_yolov5/YoloV5.py
etra_yolov5/__init__.py
etra_yolov5/external/__init__.py
yolov5_E-0.0.1.dist-info/LICENSE
yolov5_E-0.0.1.dist-info/METADATA
yolov5_E-0.0.1.dist-info/WHEEL
yolov5_E-0.0.1.dist-info/top_level.txt
yolov5_E-0.0.1.dist-info/RECORD
