Metadata-Version: 2.1
Name: yolov5-E
Version: 0.0.1
Summary: Simplified yolov5 version
Home-page: http://gitlabnew.depid.local/python-packages/etra-yolov5
Author: Sergi Grau
Author-email: sgrau.etraid@grupoetra.com
License: MIT
Keywords: YoloV5
Classifier: Programming Language :: Python :: 3
Classifier: License :: OSI Approved :: MIT License
Classifier: Operating System :: OS Independent
Requires-Python: ==3.8
License-File: LICENSE
Requires-Dist: absl-py (==1.0.0)
Requires-Dist: bleach (==5.0.0)
Requires-Dist: build (==0.7.0)
Requires-Dist: cachetools (==5.1.0)
Requires-Dist: certifi (==2022.5.18)
Requires-Dist: charset-normalizer (==2.0.12)
Requires-Dist: colorama (==0.4.4)
Requires-Dist: commonmark (==0.9.1)
Requires-Dist: cycler (==0.11.0)
Requires-Dist: docutils (==0.18.1)
Requires-Dist: flatbuffers (==2.0)
Requires-Dist: fonttools (==4.33.3)
Requires-Dist: google-auth (==2.6.6)
Requires-Dist: google-auth-oauthlib (==0.4.6)
Requires-Dist: grpcio (==1.46.1)
Requires-Dist: idna (==3.3)
Requires-Dist: importlib-metadata (==4.11.3)
Requires-Dist: keyring (==23.5.0)
Requires-Dist: kiwisolver (==1.4.2)
Requires-Dist: Markdown (==3.3.7)
Requires-Dist: matplotlib (==3.5.2)
Requires-Dist: numpy (==1.22.3)
Requires-Dist: oauthlib (==3.2.0)
Requires-Dist: onnxruntime (==1.11.1)
Requires-Dist: opencv-python (==4.5.5.64)
Requires-Dist: packaging (==21.3)
Requires-Dist: pandas (==1.4.2)
Requires-Dist: pep517 (==0.12.0)
Requires-Dist: Pillow (==9.1.1)
Requires-Dist: pkginfo (==1.8.2)
Requires-Dist: protobuf (==3.20.1)
Requires-Dist: pyasn1 (==0.4.8)
Requires-Dist: pyasn1-modules (==0.2.8)
Requires-Dist: Pygments (==2.12.0)
Requires-Dist: pyparsing (==3.0.9)
Requires-Dist: python-dateutil (==2.8.2)
Requires-Dist: pytz (==2022.1)
Requires-Dist: pywin32-ctypes (==0.2.0)
Requires-Dist: PyYAML (==6.0)
Requires-Dist: readme-renderer (==35.0)
Requires-Dist: requests (==2.27.1)
Requires-Dist: requests-oauthlib (==1.3.1)
Requires-Dist: requests-toolbelt (==0.9.1)
Requires-Dist: rfc3986 (==2.0.0)
Requires-Dist: rich (==12.4.1)
Requires-Dist: rsa (==4.8)
Requires-Dist: scipy (==1.8.1)
Requires-Dist: seaborn (==0.11.2)
Requires-Dist: six (==1.16.0)
Requires-Dist: tensorboard (==2.9.0)
Requires-Dist: tensorboard-data-server (==0.6.1)
Requires-Dist: tensorboard-plugin-wit (==1.8.1)
Requires-Dist: thop (==0.0.31.post2005241907)
Requires-Dist: tomli (==2.0.1)
Requires-Dist: tqdm (==4.64.0)
Requires-Dist: twine (==4.0.0)
Requires-Dist: typing-extensions (==4.2.0)
Requires-Dist: urllib3 (==1.26.9)
Requires-Dist: webencodings (==0.5.1)
Requires-Dist: Werkzeug (==2.1.2)
Requires-Dist: zipp (==3.8.0)
